elphick/sklearn_viz/__init__.py
elphick/sklearn_viz/components/__init__.py
elphick/sklearn_viz/components/estimators.py
elphick/sklearn_viz/components/kfold.py
elphick/sklearn_viz/features/__init__.py
elphick/sklearn_viz/features/importance.py
elphick/sklearn_viz/features/outlier_detection.py
elphick/sklearn_viz/features/parallel_coordinates.py
elphick/sklearn_viz/features/principal_components.py
elphick/sklearn_viz/features/scatter_matrix.py
elphick/sklearn_viz/model_selection/__init__.py
elphick/sklearn_viz/model_selection/cross_validation.py
elphick/sklearn_viz/model_selection/learning_curve.py
elphick/sklearn_viz/model_selection/metrics.py
elphick/sklearn_viz/model_selection/model_selection.py
elphick/sklearn_viz/model_selection/models.py
elphick/sklearn_viz/model_selection/scorers.py
elphick/sklearn_viz/residuals/__init__.py
elphick/sklearn_viz/residuals/error.py
elphick/sklearn_viz/utils/__init__.py
elphick/sklearn_viz/utils/file.py
elphick/sklearn_viz/utils/plotly.py
elphick/sklearn_viz/utils/timer.py
sklearn_viz-0.6.10.dist-info/entry_points.txt
sklearn_viz-0.6.10.dist-info/LICENSE
sklearn_viz-0.6.10.dist-info/METADATA
sklearn_viz-0.6.10.dist-info/WHEEL
sklearn_viz-0.6.10.dist-info/RECORD
