Metadata-Version: 2.1
Name: sklearn-viz
Version: 0.6.10
Summary: Interactive visualisation for scikit-learn models
Author: Greg
Author-email: 11791585+elphick@users.noreply.github.com
Requires-Python: >=3.9,<3.14
Classifier: Programming Language :: Python :: 3
Classifier: Programming Language :: Python :: 3.9
Classifier: Programming Language :: Python :: 3.10
Classifier: Programming Language :: Python :: 3.11
Classifier: Programming Language :: Python :: 3.12
Classifier: Programming Language :: Python :: 3.13
Requires-Dist: matplotlib (>=3.3)
Requires-Dist: pandas (>=1.3.0)
Requires-Dist: plotly (>=5.15.0,<6.0.0)
Requires-Dist: scikit-learn (>=1.2)
Requires-Dist: statsmodels (>=0.14.0,<0.15.0)
